hackercafe
