Metadata-Version: 1.0
Name: hackercafe
Version: 1.0.1
Summary: Python client for HackerCafe
Home-page: https://www.hackerearth.com
Author: Sreeram Boyapati
Author-email: sreeram@hackerearth.com
License: MIT
Keywords: hackerarth,hackercafe
Platform: UNKNOWN
